ubotw_converter/__init__.py
ubotw_converter/converter.py
ubotw_converter/bars_py/__init__.py
ubotw_converter/bars_py/bars.py
ubotw_converter/bars_py/bcf_converter.py
ubotw_converter/bars_py/utils.py
ubotw_converter/bflim_convertor/__init__.py
ubotw_converter/bflim_convertor/bflim_extract.py
ubotw_converter/bflim_convertor/bntx.py
ubotw_converter/bflim_convertor/bntx_dds_injector.py
ubotw_converter/bflim_convertor/dds.py
ubotw_converter/bflim_convertor/formConv.py
ubotw_converter/bflim_convertor/globals.py
ubotw_converter/bflim_convertor/addrlib/__init__.py
ubotw_converter/bflim_convertor/addrlib/addrlib.py
ubotw_converter/dotnet_libs/BfresLibrary.dll
ubotw_converter/dotnet_libs/Newtonsoft.Json.dll
ubotw_converter/dotnet_libs/Syroot.BinaryData.dll
ubotw_converter/dotnet_libs/Syroot.Maths.dll
ubotw_converter/dotnet_libs/Syroot.NintenTools.NSW.Bntx.dll
UBOTW_Converter-1.4.0a2.dist-info/METADATA
UBOTW_Converter-1.4.0a2.dist-info/WHEEL
UBOTW_Converter-1.4.0a2.dist-info/entry_points.txt
UBOTW_Converter-1.4.0a2.dist-info/top_level.txt
UBOTW_Converter-1.4.0a2.dist-info/RECORD
