Metadata-Version: 2.1
Name: UBOTW-Converter
Version: 1.4.0a2
Summary: A script to convert WiiU BotW mods to Switch
Home-page: https://github.com/Nitr4m12/UltimateBotWConverter
Author: Nitram
License: GNU General Public License v3.0
Project-URL: Bug Tracker, https://github.com/Nitr4m12/UltimateBotWConverter/issues
Platform: UNKNOWN
Classifier: Programming Language :: Python :: 3 :: Only
Classifier: License :: OSI Approved :: GNU General Public License v3 or later (GPLv3+)
Classifier: Operating System :: OS Independent
Requires-Python: >=3.7<3.9
Requires-Dist: bcml (>=3.7.2)
Requires-Dist: pythonnet (>=2.5.2)
